{
	"name": "RestResource1",
	"properties": {
		"linkedServiceName": {
			"referenceName": "LinkedService_REST_Historical_Forcast",
			"type": "LinkedServiceReference"
		},
		"parameters": {
			"appkey": {
				"type": "string",
				"defaultValue": "3b57dd0a2acb41fc8430fc63feb7e474"
			},
			"q": {
				"type": "string",
				"defaultValue": "pune"
			}
		},
		"annotations": [],
		"type": "RestResource",
		"typeProperties": {
			"relativeUrl": "http://api.openweathermap.org/data/2.5/forecast?q={0}&APPID={1}"
		},
		"schema": []
	}
}